MANIFEST.in
setup.py
moxie/__init__.py
moxie/deploy.py
moxie/music.py
moxie/transcode.py
moxie/web.py
moxie.egg-info/PKG-INFO
moxie.egg-info/SOURCES.txt
moxie.egg-info/dependency_links.txt
moxie.egg-info/entry_points.txt
moxie.egg-info/requires.txt
moxie.egg-info/top_level.txt
moxie/static/MusicPlayer.swf
moxie/static/expressInstall.swf
moxie/static/jquery-1.2.6.min.js
moxie/static/moxie.js
moxie/static/style.css
moxie/static/swfobject.js
moxie/templates/index.html
moxie/templates/rss.xml
moxie/templates/xspf.xml