Metadata-Version: 1.0
Name: moxie
Version: 8.12.1
Summary: Makes mixtapes!
Home-page: http://github.com/quad/moxie
Author: Moxie Hackers
Author-email: moxie-hackers@googlegroups.com
License: GPLv3
Platform: UNKNOWN
Classifier: Development Status :: 4 - Beta
Classifier: Environment :: Console
Classifier: Environment :: Web Environment
Classifier: License :: OSI Approved :: GNU General Public License (GPL)
Classifier: Topic :: Internet :: WWW/HTTP
Classifier: Topic :: Multimedia :: Sound/Audio :: Players :: MP3
Classifier: Topic :: Utilities
